hyperunison_public_api/UnisonSDKApi.py
hyperunison_public_api/__init__.py
hyperunison_public_api/setup.py
hyperunison_public_api/hyperunison_public_api_sdk/__init__.py
hyperunison_public_api/hyperunison_public_api_sdk/api_client.py
hyperunison_public_api/hyperunison_public_api_sdk/configuration.py
hyperunison_public_api/hyperunison_public_api_sdk/exceptions.py
hyperunison_public_api/hyperunison_public_api_sdk/model_utils.py
hyperunison_public_api/hyperunison_public_api_sdk/rest.py
hyperunison_public_api/hyperunison_public_api_sdk/api/__init__.py
hyperunison_public_api/hyperunison_public_api_sdk/api/cohort_api.py
hyperunison_public_api/hyperunison_public_api_sdk/api/pipeline_api.py
hyperunison_public_api/hyperunison_public_api_sdk/api/structure_api.py
hyperunison_public_api/hyperunison_public_api_sdk/api/suggester_api.py
hyperunison_public_api/hyperunison_public_api_sdk/apis/__init__.py
hyperunison_public_api/hyperunison_public_api_sdk/model/__init__.py
hyperunison_public_api/hyperunison_public_api_sdk/model/biobank_omop_export_response.py
hyperunison_public_api/hyperunison_public_api_sdk/model/bulk_update_structure_request.py
hyperunison_public_api/hyperunison_public_api_sdk/model/data_item_dictionary_with_accuracy_list_response.py
hyperunison_public_api/hyperunison_public_api_sdk/model/data_item_dictionary_with_accuracy_response.py
hyperunison_public_api/hyperunison_public_api_sdk/model/job.py
hyperunison_public_api/hyperunison_public_api_sdk/model/multi_run_pipeline.py
hyperunison_public_api/hyperunison_public_api_sdk/model/nextflow_pipeline_output_formatter_result.py
hyperunison_public_api/hyperunison_public_api_sdk/model/nextflow_pipeline_output_formatter_result_item_status.py
hyperunison_public_api/hyperunison_public_api_sdk/model/public_cohort_execute_query_request.py
hyperunison_public_api/hyperunison_public_api_sdk/model/response_to_ucdm_result_with_sql.py
hyperunison_public_api/hyperunison_public_api_sdk/model/run_custom_workflow_request.py
hyperunison_public_api_sdk-2.3.5.dist-info/licenses/LICENSE
hyperunison_public_api_sdk-2.3.5.dist-info/METADATA
hyperunison_public_api_sdk-2.3.5.dist-info/WHEEL
hyperunison_public_api_sdk-2.3.5.dist-info/top_level.txt
hyperunison_public_api_sdk-2.3.5.dist-info/RECORD
