Metadata-Version: 2.4
Name: hyperunison_public_api_sdk
Version: 2.3.5
Summary: Python SDK to use public API of Unison
Author-email: Konstantin Naumov <konstantin@hyperunison.com>
Project-URL: Homepage, https://github.com/Hyperunison/unison-sdk-python
Project-URL: Issues, https://github.com/Hyperunison/unison-sdk-python/issues
Classifier: Programming Language :: Python :: 3
Classifier: Operating System :: OS Independent
Requires-Python: >=3.8
